cesnet_service_path_plugin
