Metadata-Version: 2.4
Name: cesnet_service_path_plugin
Version: 6.0.0
Summary: Adds ability to create, edit and view service paths in the network.
Author-email: Jan Krupa <jan.krupa@cesnet.cz>, Jiri Vrany <jiri.vrany@cesnet.cz>
License: Apache-2.0
Project-URL: Homepage, https://github.com/CESNET/cesnet_service_path_plugin
Project-URL: Repository, https://github.com/CESNET/cesnet_service_path_plugin
Project-URL: Issues, https://github.com/CESNET/cesnet_service_path_plugin/issues
Classifier: Development Status :: 4 - Beta
Classifier: Intended Audience :: Developers
Classifier: Framework :: Django
Classifier: License :: OSI Approved :: Apache Software License
Classifier: Operating System :: OS Independent
Classifier: Programming Language :: Python :: 3 :: Only
Classifier: Programming Language :: Python :: 3.10
Classifier: Programming Language :: Python :: 3.11
Classifier: Programming Language :: Python :: 3.12
Requires-Python: >=3.12
License-File: LICENSE
Requires-Dist: geopandas
Requires-Dist: fiona
Requires-Dist: shapely
Requires-Dist: python-dateutil
Provides-Extra: dev
Requires-Dist: black; extra == "dev"
Requires-Dist: autopep8; extra == "dev"
Requires-Dist: pip; extra == "dev"
Requires-Dist: check-manifest; extra == "dev"
Requires-Dist: pytest; extra == "dev"
Requires-Dist: python-dotenv; extra == "dev"
Dynamic: license-file
